ConanTools/Conan.py
ConanTools/Git.py
ConanTools/Hack.py
ConanTools/Repack.py
ConanTools/Version.py
ConanTools/__init__.py
ConanTools-0.4.3.dist-info/DESCRIPTION.rst
ConanTools-0.4.3.dist-info/METADATA
ConanTools-0.4.3.dist-info/RECORD
ConanTools-0.4.3.dist-info/WHEEL
ConanTools-0.4.3.dist-info/metadata.json
ConanTools-0.4.3.dist-info/top_level.txt
