Metadata-Version: 2.0
Name: ConanTools
Version: 0.4.3
Summary: Helpers and tools that make working with conan more convenient.
Home-page: https://github.com/niosHD/ConanTools
Author: Mario Werner
Author-email: nioshd@gmail.com
License: MIT
Platform: UNKNOWN
Classifier: Development Status :: 2 - Pre-Alpha
Classifier: Intended Audience :: Developers
Classifier: License :: OSI Approved :: MIT License
Classifier: Operating System :: OS Independent
Classifier: Programming Language :: Python :: 3.5
Classifier: Topic :: Software Development :: Build Tools
Classifier: Topic :: Utilities
Provides-Extra: documentation
Requires-Dist: sphinx; extra == 'documentation'
Requires-Dist: sphinx-autodoc-typehints; extra == 'documentation'
